{
  "hero": {
    "visible": true,
    "eyebrow": "Ethiopian Community Association in Atlanta",
    "title": "Building Intergenerational Connections\nand Strengthening Community Resilience",
    "description": "ECAA exists to serve, connect, and empower the Ethiopian community in Atlanta while helping preserve Ethiopian cultural heritage and support integration into American society.",
    "trustCue": "Serving the Ethiopian community in Atlanta through connection, culture, and support.",
    "primaryCta": {
      "label": "Become a Member",
      "href": "/membership"
    },
    "secondaryCta": {
      "label": "View Events",
      "href": "/events"
    },
    "supportCta": {
      "label": "Support ECAA",
      "href": "/support"
    },
    "image": "/images/home-hero-community-atlanta.jpg",
    "imageAlt": "Community members gathered in Atlanta for the Ethiopian Community Association in Atlanta."
  },
  "featuredEvents": {
    "visible": true,
    "eyebrow": "Events & News",
    "title": "Featured Events & Community Updates",
    "description": "Stay connected with important ECAA events, announcements, and community news.",
    "items": [],
    "emptyCaption": "Upcoming events and community updates will appear here soon.",
    "placeholderItems": [
      {
        "id": "preview-upcoming-events",
        "title": "Upcoming community events",
        "category": "Events",
        "excerpt": "Gatherings, celebrations, and seasonal programs for the community.",
        "image": "/images/events-community-gathering.jpg",
        "imageAlt": "Community gathering at an ECAA event."
      },
      {
        "id": "preview-announcements",
        "title": "Announcements and celebrations",
        "category": "News",
        "excerpt": "Important updates and milestones from across ECAA.",
        "image": "/images/membership-welcome.jpg",
        "imageAlt": "Welcoming community gathering for ECAA."
      },
      {
        "id": "preview-seasonal",
        "title": "Seasonal gatherings and updates",
        "category": "Community",
        "excerpt": "Cultural observances and community-wide news.",
        "image": "/images/programs-community-support.jpg",
        "imageAlt": "ECAA community support programs."
      }
    ],
    "sectionCta": {
      "label": "View All Events",
      "href": "/events"
    }
  },
  "featuredMedia": {
    "visible": true,
    "eyebrow": "Media",
    "title": "Community Moments",
    "description": "Photos and videos that highlight ECAA's community, culture, and connection.",
    "layout": "collage",
    "items": [
      {
        "id": "featured-media-video-1",
        "type": "video",
        "title": "ECAA Community Video",
        "src": "",
        "alt": "ECAA Community Video",
        "youtubeUrl": "https://youtu.be/xV1vZDTNk6k",
        "embedUrl": "https://youtu.be/xV1vZDTNk6k",
        "thumbnailUrl": "",
        "category": "Community",
        "featuredSize": "large",
        "href": "/media",
        "sourceMediaId": "ecaa-community-video",
        "notes": "Featured homepage video."
      },
      {
        "id": "featured-media-image-1",
        "type": "image",
        "title": "Community Gathering",
        "src": "/images/events-community-gathering.jpg",
        "alt": "Community gathering at an ECAA event.",
        "youtubeUrl": "",
        "embedUrl": "",
        "thumbnailUrl": "",
        "category": "Events",
        "featuredSize": "wide",
        "href": "/media",
        "sourceMediaId": "events-community-gathering",
        "notes": "Featured homepage photo."
      },
      {
        "id": "featured-media-image-2",
        "type": "image",
        "title": "Community Support",
        "src": "/images/programs-community-support.jpg",
        "alt": "ECAA community support programs.",
        "youtubeUrl": "",
        "embedUrl": "",
        "thumbnailUrl": "",
        "category": "Programs",
        "featuredSize": "small",
        "href": "/media",
        "sourceMediaId": "programs-community-support",
        "notes": "Featured homepage photo."
      },
      {
        "id": "featured-media-image-3",
        "type": "image",
        "title": "Welcome to ECAA",
        "src": "/images/membership-welcome.jpg",
        "alt": "Welcoming community gathering for ECAA membership.",
        "youtubeUrl": "",
        "embedUrl": "",
        "thumbnailUrl": "",
        "category": "Membership",
        "featuredSize": "small",
        "href": "/media",
        "sourceMediaId": "membership-welcome",
        "notes": "Featured homepage photo."
      }
    ],
    "sectionCta": {
      "label": "View Media Gallery",
      "href": "/media"
    }
  },
  "bookHall": {
    "visible": true,
    "eyebrow": "Book a Hall",
    "title": "Plan Your Next Gathering With ECAA",
    "description": "Planning a community gathering, meeting, or private event? Submit a request to learn more about hall availability.",
    "useCases": [
      "Community meetings",
      "Celebrations",
      "Workshops",
      "Cultural events"
    ],
    "details": [
      "TODO: Add verified hall booking details.",
      "TODO: Add verified availability or process."
    ],
    "primaryCta": {
      "label": "Book a Hall",
      "href": "/contact"
    },
    "secondaryCta": {
      "label": "Contact Us",
      "href": "/contact"
    },
    "image": "/images/events-community-gathering.jpg",
    "imageAlt": "Community gathering space for ECAA events.",
    "notes": "TODO: Replace /contact with official hall booking form if available."
  },
  "featuredPrograms": {
    "visible": true,
    "eyebrow": "Programs & Services",
    "title": "Featured Programs & Services",
    "description": "Explore selected ECAA programs and services that support culture, community, youth, families, and connection.",
    "items": [
      {
        "id": "featured-program-community-support",
        "title": "Community Support",
        "shortDescription": "Information, resources, and support for community members and families.",
        "href": "/programs#community-support",
        "icon": "hands",
        "image": "/images/programs-community-support.jpg",
        "imageAlt": "Community support and programs image for ECAA.",
        "sourceProgramId": "community-support",
        "notes": "Homepage featured program only."
      },
      {
        "id": "featured-program-cultural-programs",
        "title": "Cultural Programs",
        "shortDescription": "Gatherings and activities that celebrate heritage and connection.",
        "href": "/programs#cultural-programs",
        "icon": "culture",
        "image": "/images/events-community-gathering.jpg",
        "imageAlt": "Cultural community gathering for ECAA programs.",
        "sourceProgramId": "cultural-programs",
        "notes": ""
      },
      {
        "id": "featured-program-youth-education",
        "title": "Youth & Education",
        "shortDescription": "Programs that support learning, student engagement, and growth.",
        "href": "/programs#youth-education",
        "icon": "education",
        "image": "/images/leadership-community-guidance.jpg",
        "imageAlt": "Youth and education community guidance at ECAA.",
        "sourceProgramId": "youth-education",
        "notes": ""
      },
      {
        "id": "featured-program-edir",
        "title": "EDIR",
        "shortDescription": "Mutual-support structure and EDIR-related community leadership.",
        "href": "/programs#edir",
        "icon": "community",
        "image": "/images/membership-welcome.jpg",
        "imageAlt": "Community welcome and mutual support at ECAA.",
        "sourceProgramId": "edir",
        "notes": ""
      }
    ],
    "sectionCta": {
      "label": "Explore All Programs",
      "href": "/programs"
    }
  }
}
